url_content_extractor/__init__.py
url_content_extractor/server.py
url_content_extractor-0.1.3.dist-info/METADATA
url_content_extractor-0.1.3.dist-info/WHEEL
url_content_extractor-0.1.3.dist-info/entry_points.txt
url_content_extractor-0.1.3.dist-info/RECORD
