Metadata-Version: 2.4
Name: url-content-extractor
Version: 0.1.3
Summary: A simple MCP server to extract content from URLs
Requires-Python: >=3.10
Requires-Dist: beautifulsoup4
Requires-Dist: httpx
Requires-Dist: mcp[cli]
